setup.py
rpi_test/__init__.py
rpi_test/rpi_test.ctf
rpi_test.egg-info/PKG-INFO
rpi_test.egg-info/SOURCES.txt
rpi_test.egg-info/dependency_links.txt
rpi_test.egg-info/top_level.txt