Metadata-Version: 1.0
Name: rpi-test
Version: 1.0.4
Summary: A module to call RPI MATLAB primitives from Python3.6
Home-page: UNKNOWN
Author: Keyi Liu
Author-email: UNKNOWN
License: UNKNOWN
Platform: Linux
Platform: Windows
Platform: MacOS
